{"d6cde6b60e47587993fe1a657460f234":{"statistic":{"failed":1,"broken":0,"skipped":0,"passed":0,"unknown":0,"total":1},"items":[{"uid":"34a3a2b5906e3dd9","reportUrl":"https://Sunil-Kumar-Reddy-K.github.io/playwright_python_pytest/247/#testresult/34a3a2b5906e3dd9","status":"failed","statusDetails":"AssertionError: assert 503 == 200\n +  where 503 = <Response [503]>.status_code","time":{"start":1769668614709,"stop":1769668654921,"duration":40212}}]},"c164e9e395a366df276302fde86ca4c0":{"statistic":{"failed":0,"broken":1,"skipped":0,"passed":0,"unknown":0,"total":1},"items":[{"uid":"e08087ab5af4ed69","reportUrl":"https://Sunil-Kumar-Reddy-K.github.io/playwright_python_pytest/247/#testresult/e08087ab5af4ed69","status":"broken","statusDetails":"NameError: name 'email' is not defined. Did you forget to import 'email'?","time":{"start":1769668694851,"stop":1769668694851,"duration":0}}]},"c0c6348c0e87cd14bbf4110e9af35e87":{"statistic":{"failed":1,"broken":0,"skipped":0,"passed":0,"unknown":0,"total":1},"items":[{"uid":"9dbbecca790583b8","reportUrl":"https://Sunil-Kumar-Reddy-K.github.io/playwright_python_pytest/247/#testresult/9dbbecca790583b8","status":"failed","statusDetails":"AssertionError","time":{"start":1769668694853,"stop":1769668694853,"duration":0}}]},"98d23460597fd5db9fe5eea1192c46a7":{"statistic":{"failed":0,"broken":0,"skipped":0,"passed":1,"unknown":0,"total":1},"items":[{"uid":"ea645dc9cf445ecf","reportUrl":"https://Sunil-Kumar-Reddy-K.github.io/playwright_python_pytest/247/#testresult/ea645dc9cf445ecf","status":"passed","time":{"start":1769668739966,"stop":1769668744732,"duration":4766}}]},"d1dd42843ead211a39d79aa974854d31":{"statistic":{"failed":0,"broken":1,"skipped":0,"passed":0,"unknown":0,"total":1},"items":[{"uid":"8cbf06705eb8c405","reportUrl":"https://Sunil-Kumar-Reddy-K.github.io/playwright_python_pytest/247/#testresult/8cbf06705eb8c405","status":"broken","statusDetails":"requests.exceptions.JSONDecodeError: Expecting value: line 1 column 1 (char 0)","time":{"start":1769668654948,"stop":1769668694824,"duration":39876}}]},"547b9a370d970e94cbf8370fad733211":{"statistic":{"failed":0,"broken":0,"skipped":0,"passed":1,"unknown":0,"total":1},"items":[{"uid":"7c17ab2e8b11fb90","reportUrl":"https://Sunil-Kumar-Reddy-K.github.io/playwright_python_pytest/247/#testresult/7c17ab2e8b11fb90","status":"passed","time":{"start":1769668735022,"stop":1769668739866,"duration":4844}}]}}